docs/USER_GUIDE.md
sahajmails/__init__.py
sahajmails/__main__.py
sahajmails/app.py
sahajmails/cli.py
sahajmails-1.0.1.dist-info/licenses/LICENSE
tests/test_core.py
sahajmails-1.0.1.dist-info/METADATA
sahajmails-1.0.1.dist-info/WHEEL
sahajmails-1.0.1.dist-info/entry_points.txt
sahajmails-1.0.1.dist-info/top_level.txt
sahajmails-1.0.1.dist-info/RECORD
