Metadata-Version: 2.4
Name: sahajmails
Version: 1.0.1
Summary: Simple, secure bulk email sender using Gmail + Streamlit
Author-email: Sahaj Raj Malla <mallasahajraj@gmail.com>
License: MIT
Project-URL: Homepage, https://github.com/sahajrajmalla/sahajmails
Project-URL: Repository, https://github.com/sahajrajmalla/sahajmails
Project-URL: Documentation, https://github.com/sahajrajmalla/sahajmails/blob/main/docs/USER_GUIDE.md
Project-URL: Issues, https://github.com/sahajrajmalla/sahajmails/issues
Keywords: email,bulk-email,streamlit,gmail,marketing,personalization,csv
Classifier: Programming Language :: Python :: 3
Classifier: Programming Language :: Python :: 3.8
Classifier: Programming Language :: Python :: 3.9
Classifier: Programming Language :: Python :: 3.10
Classifier: Programming Language :: Python :: 3.11
Classifier: Programming Language :: Python :: 3.12
Classifier: License :: OSI Approved :: MIT License
Classifier: Operating System :: OS Independent
Classifier: Intended Audience :: End Users/Desktop
Classifier: Intended Audience :: Developers
Classifier: Topic :: Communications :: Email
Classifier: Topic :: Office/Business
Requires-Python: >=3.8
License-File: LICENSE
Requires-Dist: streamlit>=1.29.0
Requires-Dist: pandas>=2.0.0
Requires-Dist: markdown>=3.4.0
Provides-Extra: test
Requires-Dist: pytest>=7.0; extra == "test"
Provides-Extra: dev
Requires-Dist: build>=1.0; extra == "dev"
Requires-Dist: twine>=4.0; extra == "dev"
Requires-Dist: black>=23.0; extra == "dev"
Requires-Dist: flake8>=6.0; extra == "dev"
Requires-Dist: pytest>=7.0; extra == "dev"
Dynamic: license-file
